rsd_tts/__init__.py
rsd_tts/core.py
rsd_tts/utils.py
rsd_tts_rsddev-0.1.5.dist-info/licenses/LICENSE
rsd_tts_rsddev-0.1.5.dist-info/METADATA
rsd_tts_rsddev-0.1.5.dist-info/WHEEL
rsd_tts_rsddev-0.1.5.dist-info/top_level.txt
rsd_tts_rsddev-0.1.5.dist-info/RECORD
