Metadata-Version: 2.4
Name: rsd_tts_RsdDev
Version: 0.1.5
Summary: Libreria Python per sintesi vocale in italiano con pulizia del testo (win 10/11)
Author: Reza Shahrezaei
License: MIT
Project-URL: Homepage, https://github.com/RezaSD-Dev/rsd_tts
Project-URL: Documentation, https://github.com/RezaSD-Dev/rsd_tts#readme
Keywords: text-to-speech,italiano,TTS,sintesi vocale
Classifier: Operating System :: Microsoft :: Windows :: Windows 10
Classifier: Operating System :: Microsoft :: Windows :: Windows 11
Classifier: Environment :: Win32 (MS Windows)
Classifier: Development Status :: 3 - Alpha
Classifier: Intended Audience :: Developers
Classifier: License :: OSI Approved :: MIT License
Classifier: Natural Language :: Italian
Requires-Python: >=3.7
License-File: LICENSE
Requires-Dist: pywin32>=300
Dynamic: license-file
